{
  "routes": [
    {
      "method": "GET",
      "path": "/forms-of-reconnaissances",
      "handler": "forms-of-reconnaissance.find",
      "config": {
        "policies": []
      }
    },
    {
      "method": "GET",
      "path": "/forms-of-reconnaissances/count",
      "handler": "forms-of-reconnaissance.count",
      "config": {
        "policies": []
      }
    },
    {
      "method": "GET",
      "path": "/forms-of-reconnaissances/:id",
      "handler": "forms-of-reconnaissance.findOne",
      "config": {
        "policies": []
      }
    },
    {
      "method": "POST",
      "path": "/forms-of-reconnaissances",
      "handler": "forms-of-reconnaissance.create",
      "config": {
        "policies": []
      }
    },
    {
      "method": "PUT",
      "path": "/forms-of-reconnaissances/:id",
      "handler": "forms-of-reconnaissance.update",
      "config": {
        "policies": []
      }
    },
    {
      "method": "DELETE",
      "path": "/forms-of-reconnaissances/:id",
      "handler": "forms-of-reconnaissance.delete",
      "config": {
        "policies": []
      }
    }
  ]
}
